ddnosh_mcp_demo/__init__.py
ddnosh_mcp_demo-0.1.0.dist-info/WHEEL
ddnosh_mcp_demo-0.1.0.dist-info/entry_points.txt
ddnosh_mcp_demo-0.1.0.dist-info/METADATA
ddnosh_mcp_demo-0.1.0.dist-info/RECORD
