Metadata-Version: 2.3
Name: ddnosh-mcp-demo
Version: 0.1.0
Summary: Add your description here
Author: ddnosh
Author-email: ddnosh <ddnosh@hotmail.com>
Requires-Dist: mcp[cli]>=1.15.0
Requires-Python: >=3.13.7
